gresearch/__init__.py
gresearch/spark/__init__.py
gresearch/spark/diff/__init__.py
gresearch/spark/diff/comparator/__init__.py
gresearch/spark/parquet/__init__.py
pyspark/jars/spark-extension_2.13-2.15.0-4.0.jar
pyspark_extension-2.15.0.4.0.dist-info/METADATA
pyspark_extension-2.15.0.4.0.dist-info/WHEEL
pyspark_extension-2.15.0.4.0.dist-info/top_level.txt
pyspark_extension-2.15.0.4.0.dist-info/RECORD
