Metadata-Version: 2.4
Name: pyspark-extension
Version: 2.15.0.4.0
Summary: A library that provides useful extensions to Apache Spark.
Home-page: https://github.com/G-Research/spark-extension
Author: Enrico Minack
Author-email: github@enrico.minack.dev
License: http://www.apache.org/licenses/LICENSE-2.0.html
Classifier: Development Status :: 5 - Production/Stable
Classifier: License :: OSI Approved :: Apache Software License
Classifier: Programming Language :: Python :: 3
Classifier: Programming Language :: Python :: 3.7
Classifier: Programming Language :: Python :: 3.8
Classifier: Programming Language :: Python :: 3.9
Classifier: Programming Language :: Python :: 3.10
Classifier: Programming Language :: Python :: 3.11
Classifier: Programming Language :: Python :: 3.12
Classifier: Programming Language :: Python :: 3.13
Classifier: Programming Language :: Python :: Implementation :: CPython
Classifier: Programming Language :: Python :: Implementation :: PyPy
Classifier: Typing :: Typed
Requires-Python: >=3.7
Requires-Dist: typing_extensions
Provides-Extra: test
Requires-Dist: pandas>=1.0.5; extra == "test"
Requires-Dist: py4j; extra == "test"
Requires-Dist: pyarrow>=4.0.0; extra == "test"
Requires-Dist: pyspark~=4.0.0; extra == "test"
Requires-Dist: pytest; extra == "test"
Requires-Dist: unittest-xml-reporting; extra == "test"
Dynamic: author
Dynamic: author-email
Dynamic: classifier
Dynamic: description
Dynamic: description-content-type
Dynamic: home-page
Dynamic: license
Dynamic: provides-extra
Dynamic: requires-dist
Dynamic: requires-python
Dynamic: summary
